xorq_datafusion-0.2.4.dist-info/METADATA
xorq_datafusion-0.2.4.dist-info/WHEEL
xorq_datafusion-0.2.4.dist-info/licenses/LICENSE
xorq_datafusion/__init__.py
xorq_datafusion/_internal.abi3.so
xorq_datafusion-0.2.4.dist-info/RECORD
