Metadata-Version: 2.4
Name: xorq-datafusion
Version: 0.2.4
Classifier: Programming Language :: Rust
Classifier: Programming Language :: Python :: Implementation :: CPython
Classifier: Programming Language :: Python :: Implementation :: PyPy
Requires-Dist: pyarrow>=18.0.0,<22 ; python_full_version >= '3.10' and python_full_version < '4.0'
License-File: LICENSE
Requires-Python: >=3.10
